crsspd/__init__.py
crsspd/req_tools.py
crsspd/selm_tools.py
crsspd/spider.py
crsspd-1.3.0.dist-info/LICENSE
crsspd-1.3.0.dist-info/METADATA
crsspd-1.3.0.dist-info/WHEEL
crsspd-1.3.0.dist-info/top_level.txt
crsspd-1.3.0.dist-info/RECORD
